ipyaudioworklet/__init__.py
ipyaudioworklet/_frontend.py
ipyaudioworklet/_version.py
ipyaudioworklet/audio.py
ipyaudioworklet/labextension/build_log.json
ipyaudioworklet/labextension/package.json
ipyaudioworklet/labextension/static/audio-processor.js
ipyaudioworklet/labextension/static/lib_index_js.9794abb2ca76aaef3c18.js
ipyaudioworklet/labextension/static/lib_index_js.9794abb2ca76aaef3c18.js.map
ipyaudioworklet/labextension/static/lib_plugin_js.5398a952607938881d30.js
ipyaudioworklet/labextension/static/lib_plugin_js.5398a952607938881d30.js.map
ipyaudioworklet/labextension/static/lib_widget_js.227c88f975160176e66d.js
ipyaudioworklet/labextension/static/lib_widget_js.227c88f975160176e66d.js.map
ipyaudioworklet/labextension/static/remoteEntry.961c77b7098db87f3963.js
ipyaudioworklet/labextension/static/remoteEntry.961c77b7098db87f3963.js.map
ipyaudioworklet/labextension/static/style.js
ipyaudioworklet/labextension/static/vendors-node_modules_jupyter-dataserializers_lib_index_js.fe69843d13a09374b3df.js
ipyaudioworklet/labextension/static/vendors-node_modules_jupyter-dataserializers_lib_index_js.fe69843d13a09374b3df.js.map
ipyaudioworklet/nbextension/extension.js
ipyaudioworklet/nbextension/index.js
ipyaudioworklet/nbextension/index.js.LICENSE.txt
ipyaudioworklet/nbextension/index.js.map
ipyaudioworklet/nbextension/static/.gitkeep
ipyaudioworklet/nbextension/static/audio-processor.js
ipyaudioworklet/tests/__init__.py
ipyaudioworklet/tests/conftest.py
ipyaudioworklet/tests/test_audio.py
ipyaudioworklet/tests/test_nbextension_path.py
ipyaudioworklet-0.6.0.data/data/share/jupyter/nbextensions/ipyaudioworklet/extension.js
ipyaudioworklet-0.6.0.data/data/share/jupyter/nbextensions/ipyaudioworklet/index.js
ipyaudioworklet-0.6.0.data/data/share/jupyter/nbextensions/ipyaudioworklet/index.js.LICENSE.txt
ipyaudioworklet-0.6.0.data/data/share/jupyter/nbextensions/ipyaudioworklet/index.js.map
ipyaudioworklet-0.6.0.dist-info/METADATA
ipyaudioworklet-0.6.0.dist-info/WHEEL
ipyaudioworklet-0.6.0.dist-info/licenses/LICENSE.txt
ipyaudioworklet-0.6.0.dist-info/RECORD
